pyidxp/__init__.py
pyidxp/configurator.py
pyidxp/aws/__init__.py
pyidxp/aws/base.py
pyidxp/aws/dynamodb.py
pyidxp/aws/s3.py
pyidxp-0.3.3.dist-info/DESCRIPTION.rst
pyidxp-0.3.3.dist-info/METADATA
pyidxp-0.3.3.dist-info/metadata.json
pyidxp-0.3.3.dist-info/RECORD
pyidxp-0.3.3.dist-info/top_level.txt
pyidxp-0.3.3.dist-info/WHEEL
