Metadata-Version: 2.0
Name: pyidxp
Version: 0.3.3
Summary: pyidxp - simple libs for our everyday needs
Home-page: https://github.com/idxp/pyidxp
Author: Artur Rodrigues, Denis Lins
Author-email: arturhoo@gmail.com, denis.lins@outlook.com
License: LICENSE
Download-URL: https://github.com/idxp/pyidxp/tarball/0.3.3
Platform: UNKNOWN
Requires-Dist: boto (>=2.38)
Requires-Dist: python-consul (>=0.4)
